{"movie-duration":["\n                        30min\n                    "],"movie-rating-count":["477"],"movie-rating-value":["5.8"],"movie-best-rating":["10"],"movie-year":[],"movie-director":["Larry Gelbart","Harry Morgan","Jamie Farr","William Christopher","See full cast & crew"],"movie-description":["    The Korean War has ended. Colonel Potter, Sergeant Klinger, and Father Mulcahy find themselves together once again, this time at a veteran's hospital."],"movie-title":["After MASH (TV Series 1983–1985)"],"movie-image":["https://m.media-amazon.com/images/M/MV5BZGI4YjkyZTgtODdlMS00OWVjLTk3ZDYtYzI1ODgyM2QwM2MzXkEyXkFqcGdeQXVyNjExODE1MDc@._V1_UY1200_CR93,0,630,1200_AL_.jpg"],"movie-short-description":["Created by Larry Gelbart.  With Harry Morgan, Jamie Farr, William Christopher, Rosalind Chao. The Korean War has ended. Colonel Potter, Sergeant Klinger, and Father Mulcahy find themselves together once again, this time at a veteran's hospital."],"movie-url":["http://www.imdb.com/title/tt0084969/"],"movie-id":["tt0084969"],"movie-character":["30 episodes, 1983-1985\n                        ","30 episodes, 1983-1985\n                        ","30 episodes, 1983-1985\n                        ","30 episodes, 1983-1985\n                        ","30 episodes, 1983-1985\n                        ","21 episodes, 1983-1984\n                        ","19 episodes, 1983-1984\n                        ","18 episodes, 1983-1984\n                        ","15 episodes, 1984-1985\n                        ","13 episodes, 1983-1984\n                        "],"movie-actor-img":["https://m.media-amazon.com/images/G/01/imdb/images/nopicture/32x44/name-2138558783._CB470041625_.png","https://m.media-amazon.com/images/G/01/imdb/images/nopicture/32x44/name-2138558783._CB470041625_.png","https://m.media-amazon.com/images/G/01/imdb/images/nopicture/32x44/name-2138558783._CB470041625_.png","https://m.media-amazon.com/images/G/01/imdb/images/nopicture/32x44/name-2138558783._CB470041625_.png","https://m.media-amazon.com/images/G/01/imdb/images/nopicture/32x44/name-2138558783._CB470041625_.png","https://m.media-amazon.com/images/G/01/imdb/images/nopicture/32x44/name-2138558783._CB470041625_.png"],"movie-actor":["Harry Morgan","Jamie Farr","William Christopher","Rosalind Chao","Brandis Kemp","Barbara Townsend","John Chappell","Patrick Cranshaw","David Ackroyd","Lois Foraker"]}