{"movie-duration":["\n                        55min\n                    "],"movie-rating-count":["78,642"],"movie-rating-value":["8.7"],"movie-best-rating":["10"],"movie-year":[],"movie-director":["Tom Fontana","Ernie Hudson","J.K. Simmons","Lee Tergesen","See full cast & crew"],"movie-description":["    OZ chronicles the attempts of McManus (Terry Kinney) to keep control over the inmates of Em(erald) City as well as the drug trade and the violence. There have been many groups of inmates during the run of the show and not everybody makes it out alive. There's the gangstas (Adebisi, Wangler, Redding, Poet, Keene, Supreme Allah), Muslims (Said, Arif, Hamid Khan), Italians (Pancamo, Nappa, Schiebetta), bikers (Hoyt), Aryans (Schillinger, Robson, Mark Mack), Christians (Cloutier, Cudney), Latinos (Alvarez, Morales, Guerra, Hernandez), gays (Hanlon, Cramer) and a whole pile of others (the O'Riley brothers, Keller, Stanislovsky, etc.). And there's a great \"everyman\" character called Beecher who gives a good look at a normal man who made one tragic mistake. Besides the regular inmates, there's guest stars such as Method Man, Luke Perry, Master P, Treach, etc. and a bunch of prison staff doctors (Dr. Nathan), a nun/psychologist (Sister Peter Marie), a bunch of guards some honest, some crooked..."],"movie-title":["Oz (TV Series 1997–2003)"],"movie-image":["https://m.media-amazon.com/images/M/MV5BZGU0Zjc5ZGQtYzBhNi00NDFhLWE5MWEtMjQxNGFhMGJmOWM0XkEyXkFqcGdeQXVyNzkwMjQ5NzM@._V1_UY1200_CR90,0,630,1200_AL_.jpg"],"movie-short-description":["Created by Tom Fontana.  With Ernie Hudson, J.K. Simmons, Lee Tergesen, Dean Winters. A series chronicling the daily activities of an unusual prison facility and its criminal inhabitants."],"movie-url":["http://www.imdb.com/title/tt0118421/"],"movie-id":["tt0118421"],"movie-character":["Warden Leo Glynn","56 episodes, 1997-2003\n                        ","Vern Schillinger","56 episodes, 1997-2003\n                        ","Tobias Beecher","56 episodes, 1997-2003\n                        ","Ryan O'Reily","56 episodes, 1997-2003\n                        ","Bob Rebadow","56 episodes, 1997-2003\n                        ","Tim McManus","55 episodes, 1997-2003\n                        ","Sister Peter Marie Reimondo","55 episodes, 1997-2003\n                        ","Augustus Hill","55 episodes, 1997-2003\n                        ","Kareem Said","51 episodes, 1997-2003\n                        ","Poet","49 episodes, 1997-2003\n                        ","Dr. Gloria Nathan","48 episodes, 1997-2003\n                        ","Zahir Arif","48 episodes, 1997-2003\n                        ","Agamemnon Busmalis","47 episodes, 1998-2003\n                        ","Miguel Alvarez","48 episodes, 1997-2003\n                        ","Father Ray Mukada","46 episodes, 1997-2003\n                        ","Chucky Pancamo","46 episodes, 1998-2003\n                        ","46 episodes, 1997-2003\n                        ","Cyril O'Reily","45 episodes, 1998-2003\n                        ","Chico Guerra","40 episodes, 1998-2003\n                        ","Chris Keller","38 episodes, 1998-2003\n                        ","Officer Sean Murphy","38 episodes, 1999-2003\n                        ","James Robson","36 episodes, 1998-2003\n                        ","35 episodes, 1999-2003\n                        ","34 episodes, 1999-2003\n                        ","33 episodes, 1998-2003\n                        ","Simon Adebisi","32 episodes, 1997-2000\n                        ","32 episodes, 1997-2003\n                        ","Governor James Devlin","27 episodes, 1997-2003\n                        ","27 episodes, 1999-2003\n                        ","Enrique Morales","26 episodes, 2000-2003\n                        ","Timmy Kirk","26 episodes, 1998-2003\n                        ","Burr Redding","23 episodes, 2001-2003\n                        ","Officer Diane Whittlesey","23 episodes, 1997-2000\n                        ","Kenny Wangler","23 episodes, 1997-2000\n                        "],"movie-actor-img":["https://m.media-amazon.com/images/G/01/imdb/images/nopicture/32x44/name-2138558783._CB470041625_.png","https://m.media-amazon.com/images/G/01/imdb/images/nopicture/32x44/name-2138558783._CB470041625_.png","https://m.media-amazon.com/images/G/01/imdb/images/nopicture/32x44/name-2138558783._CB470041625_.png","https://m.media-amazon.com/images/G/01/imdb/images/nopicture/32x44/name-2138558783._CB470041625_.png","https://m.media-amazon.com/images/G/01/imdb/images/nopicture/32x44/name-2138558783._CB470041625_.png","https://m.media-amazon.com/images/G/01/imdb/images/nopicture/32x44/name-2138558783._CB470041625_.png","https://m.media-amazon.com/images/G/01/imdb/images/nopicture/32x44/name-2138558783._CB470041625_.png","https://m.media-amazon.com/images/G/01/imdb/images/nopicture/32x44/name-2138558783._CB470041625_.png","https://m.media-amazon.com/images/G/01/imdb/images/nopicture/32x44/name-2138558783._CB470041625_.png","https://m.media-amazon.com/images/G/01/imdb/images/nopicture/32x44/name-2138558783._CB470041625_.png","https://m.media-amazon.com/images/G/01/imdb/images/nopicture/32x44/name-2138558783._CB470041625_.png","https://m.media-amazon.com/images/G/01/imdb/images/nopicture/32x44/name-2138558783._CB470041625_.png","https://m.media-amazon.com/images/G/01/imdb/images/nopicture/32x44/name-2138558783._CB470041625_.png","https://m.media-amazon.com/images/G/01/imdb/images/nopicture/32x44/name-2138558783._CB470041625_.png","https://m.media-amazon.com/images/G/01/imdb/images/nopicture/32x44/name-2138558783._CB470041625_.png","https://m.media-amazon.com/images/G/01/imdb/images/nopicture/32x44/name-2138558783._CB470041625_.png","https://m.media-amazon.com/images/G/01/imdb/images/nopicture/32x44/name-2138558783._CB470041625_.png","https://m.media-amazon.com/images/G/01/imdb/images/nopicture/32x44/name-2138558783._CB470041625_.png","https://m.media-amazon.com/images/G/01/imdb/images/nopicture/32x44/name-2138558783._CB470041625_.png","https://m.media-amazon.com/images/G/01/imdb/images/nopicture/32x44/name-2138558783._CB470041625_.png","https://m.media-amazon.com/images/G/01/imdb/images/nopicture/32x44/name-2138558783._CB470041625_.png","https://m.media-amazon.com/images/G/01/imdb/images/nopicture/32x44/name-2138558783._CB470041625_.png","https://m.media-amazon.com/images/G/01/imdb/images/nopicture/32x44/name-2138558783._CB470041625_.png","https://m.media-amazon.com/images/G/01/imdb/images/nopicture/32x44/name-2138558783._CB470041625_.png","https://m.media-amazon.com/images/G/01/imdb/images/nopicture/32x44/name-2138558783._CB470041625_.png","https://m.media-amazon.com/images/G/01/imdb/images/nopicture/32x44/name-2138558783._CB470041625_.png","https://m.media-amazon.com/images/G/01/imdb/images/nopicture/32x44/name-2138558783._CB470041625_.png","https://m.media-amazon.com/images/G/01/imdb/images/nopicture/32x44/name-2138558783._CB470041625_.png","https://m.media-amazon.com/images/G/01/imdb/images/nopicture/32x44/name-2138558783._CB470041625_.png"],"movie-actor":["Ernie Hudson","J.K. Simmons","Lee Tergesen","Dean Winters","George Morfogen","Terry Kinney","Rita Moreno","Harold Perrineau","Eamonn Walker","Craig muMs Grant","Luna Lauren Velez","Granville Adams","Tom Mardirosian","Kirk Acevedo","BD Wong","Chuck Zito","Philip Scozzarella","Scott William Winters","Otto Sanchez","Christopher Meloni","Robert Clohessy","R.E. Rodgers","Kristin Rohde","Carl DiMaggio","Evan Seinfeld","Adewale Akinnuoye-Agbaje","Timothy L. Brown","Zeljko Ivanek","Steven Wishnoff","David Zayas","Sean Dugan","Anthony Chisholm","Edie Falco","J.D. Williams"]}